somatic/__init__.py
somatic_lm-0.0.1.dist-info/METADATA
somatic_lm-0.0.1.dist-info/WHEEL
somatic_lm-0.0.1.dist-info/licenses/LICENSE
somatic_lm-0.0.1.dist-info/RECORD
